tobikodata/__init__.py
tobikodata/http_client/__init__.py
tobikodata/http_client/api.py
tobikodata/http_client/auth.py
tobikodata/http_client/public.py
tobikodata/http_client/py.typed
tobikodata/http_client/api_models/v1/common.py
tobikodata/http_client/api_models/v1/dags.py
tobikodata/http_client/api_models/v1/evaluations.py
tobikodata/http_client/api_models/v1/runs.py
tobiko_cloud_api_client-202602.3.0.dist-info/METADATA
tobiko_cloud_api_client-202602.3.0.dist-info/WHEEL
tobiko_cloud_api_client-202602.3.0.dist-info/namespace_packages.txt
tobiko_cloud_api_client-202602.3.0.dist-info/top_level.txt
tobiko_cloud_api_client-202602.3.0.dist-info/RECORD
