Metadata-Version: 2.4
Name: tobiko-cloud-api-client
Version: 202602.3.0
Author: TobikoData Inc.
Author-email: engineering@tobikodata.com
Requires-Python: <3.13,>=3.9
Requires-Dist: authlib
Requires-Dist: httpx
Requires-Dist: pydantic[email]>=2.0.0
Requires-Dist: ruamel-yaml
Requires-Dist: tenacity
Requires-Dist: tobiko-cloud-helpers==202602.3.0
Requires-Dist: tobiko-cloud-pydantic==202602.3.0
Requires-Dist: typing-extensions
Dynamic: author
Dynamic: author-email
Dynamic: requires-dist
Dynamic: requires-python
